gb_probability_distributions/Binomialdistribution.py
gb_probability_distributions/Gaussiandistribution.py
gb_probability_distributions/Generaldistribution.py
gb_probability_distributions/__init__.py
gb_probability_distributions-0.2.dist-info/DESCRIPTION.rst
gb_probability_distributions-0.2.dist-info/METADATA
gb_probability_distributions-0.2.dist-info/RECORD
gb_probability_distributions-0.2.dist-info/WHEEL
gb_probability_distributions-0.2.dist-info/metadata.json
gb_probability_distributions-0.2.dist-info/top_level.txt
